hyperspace_rpc/__init__.py
hyperspace_rpc/hrpc.proto
hyperspace_rpc/hrpc_grpc.py
hyperspace_rpc/hrpc_pb2.py
hyperspace_rpc/schema.proto
hyperspace_rpc/schema_grpc.py
hyperspace_rpc/schema_pb2.py
hyperspace_rpc-0.0.1a3.dist-info/LICENSE
hyperspace_rpc-0.0.1a3.dist-info/WHEEL
hyperspace_rpc-0.0.1a3.dist-info/METADATA
hyperspace_rpc-0.0.1a3.dist-info/RECORD
